modelon/__init__.py
modelon/impact/__init__.py
modelon/impact/client/__init__.py
modelon/impact/client/client.py
modelon/impact/client/configuration.py
modelon/impact/client/credential_manager.py
modelon/impact/client/entities/__init__.py
modelon/impact/client/entities/asserts.py
modelon/impact/client/entities/case.py
modelon/impact/client/entities/content.py
modelon/impact/client/entities/custom_artifact.py
modelon/impact/client/entities/custom_function.py
modelon/impact/client/entities/experiment.py
modelon/impact/client/entities/external_result.py
modelon/impact/client/entities/file_uri.py
modelon/impact/client/entities/interfaces/__init__.py
modelon/impact/client/entities/interfaces/case.py
modelon/impact/client/entities/interfaces/custom_artifact.py
modelon/impact/client/entities/interfaces/custom_function.py
modelon/impact/client/entities/interfaces/experiment.py
modelon/impact/client/entities/interfaces/external_result.py
modelon/impact/client/entities/interfaces/model.py
modelon/impact/client/entities/interfaces/model_executable.py
modelon/impact/client/entities/interfaces/workspace.py
modelon/impact/client/entities/log.py
modelon/impact/client/entities/model.py
modelon/impact/client/entities/model_executable.py
modelon/impact/client/entities/project.py
modelon/impact/client/entities/result.py
modelon/impact/client/entities/status.py
modelon/impact/client/entities/workspace.py
modelon/impact/client/exceptions.py
modelon/impact/client/experiment_definition/__init__.py
modelon/impact/client/experiment_definition/asserts.py
modelon/impact/client/experiment_definition/expansion.py
modelon/impact/client/experiment_definition/extension.py
modelon/impact/client/experiment_definition/fmu_based.py
modelon/impact/client/experiment_definition/interfaces/__init__.py
modelon/impact/client/experiment_definition/interfaces/definition.py
modelon/impact/client/experiment_definition/interfaces/expansion.py
modelon/impact/client/experiment_definition/interfaces/extension.py
modelon_impact_client-4.10.3.dist-info/LICENSE.md
modelon_impact_client-4.10.3.dist-info/METADATA
modelon_impact_client-4.10.3.dist-info/WHEEL
modelon_impact_client-4.10.3.dist-info/RECORD
