Metadata-Version: 2.1
Name: modelon-impact-client
Version: 4.10.3
Summary: Client library for easy scripting against Modelon Impact
Home-page: https://www.modelon.com/modelon-impact
License: BSD
Keywords: impact,client,API
Author: WEP
Author-email: impact@modelon.com
Requires-Python: >=3.8.0,<4.0.0
Classifier: License :: Other/Proprietary License
Classifier: Programming Language :: Python :: 3
Classifier: Programming Language :: Python :: 3.8
Classifier: Programming Language :: Python :: 3.9
Classifier: Programming Language :: Python :: 3.10
Classifier: Programming Language :: Python :: 3.11
Requires-Dist: requests (>=2.23,<3.0)
Requires-Dist: semantic_version (>=2.8.5,<3.0.0)
Requires-Dist: types-requests (>=2.27.30,<3.0.0)
Requires-Dist: typing-extensions (>=4.12.2,<5.0.0)
Project-URL: Documentation, https://modelon-impact-client.readthedocs.io
Project-URL: Repository, https://github.com/modelon-community/impact-client-python
